{
    "name": "Tajik",
    "script": "cyrl",
    "type": "suffix",
    "lang": {
        "iso": "tgk",
        "html": "tg"
    },
    "data": [
        ["a", "а"],
        ["b", "б"],
        ["v", "в"],
        ["g", "г"],
        ["g`", "ғ"],
        ["d", "д"],
        ["e", "е"],
        ["jo", "ё"],
        ["zh", "ж"],
        ["z", "з"],
        ["i", "и"],
        ["j", "й"],
        ["j`", "ӣ"],
        ["k", "к"],
        ["q", "қ"],
        ["l", "л"],
        ["m", "м"],
        ["n", "н"],
        ["o", "о"],
        ["p", "п"],
        ["r", "р"],
        ["s", "с"],
        ["t", "т"],
        ["u", "у"],
        ["u`", "ӯ"],
        ["f", "ф"],
        ["x", "х"],
        ["h", "ҳ"],
        ["c", "ч"],
        ["c`", "ҷ"],
        ["sh", "ш"],
        ["#", "ъ"],
        ["je", "э"],
        ["ju", "ю"],
        ["ja", "я"],
    
        ["A", "А"],
        ["B", "Б"],
        ["V", "В"],
        ["G", "Г"],
        ["G`", "Ғ"],
        ["D", "Д"],
        ["E", "Е"],
        ["Jo", "Ё"],
        ["Zh", "Ж"],
        ["Z", "З"],
        ["I", "И"],
        ["J", "Й"],
        ["J`", "Ӣ"],
        ["K", "К"],
        ["Q", "Қ"],
        ["L", "Л"],
        ["M", "М"],
        ["N", "Н"],
        ["O", "О"],
        ["P", "П"],
        ["R", "Р"],
        ["S", "С"],
        ["T", "Т"],
        ["U", "У"],
        ["U`", "Ӯ"],
        ["F", "Ф"],
        ["X", "Х"],
        ["X`", "Ҳ"],
        ["C", "Ч"],
        ["C`", "Ҷ"],
        ["Sh", "Ш"],
        ["##", "Ъ"],
        ["Je", "Э"],
        ["Ju", "Ю"],
        ["Ja", "Я"]
    ]
}